{"cameraMode":{"drawMode":0,"name":"Shaded","section":"Shading Mode"},"sceneLighting":false,"audioPlay":false,"sceneViewState":{"m_AlwaysRefresh":false,"showFog":true,"showSkybox":false,"showFlares":true,"showImageEffects":true,"showParticleSystems":true,"showVisualEffectGraphs":true,"m_FxEnabled":true},"in2DMode":false,"pivot":{"x":-142.9977569580078,"y":-255.1354522705078,"z":-45.72528076171875},"rotation":{"x":0.30032268166542055,"y":-0.6441649198532105,"z":0.3052319586277008,"w":0.6338142156600952},"size":267.1250915527344,"orthographic":false}